initsystem.py
initsystem-0.2.0.dist-info/WHEEL
initsystem-0.2.0.dist-info/METADATA
initsystem-0.2.0.dist-info/RECORD
